pyi2c/__init__.py
pyi2c/pyi2c.py
pyi2c-0.3.1.dist-info/LICENSE
pyi2c-0.3.1.dist-info/METADATA
pyi2c-0.3.1.dist-info/WHEEL
pyi2c-0.3.1.dist-info/top_level.txt
pyi2c-0.3.1.dist-info/RECORD
