Metadata-Version: 2.1
Name: pyi2c
Version: 0.3.1
Summary: A useful i2c package for Pi
Home-page: https://github.com/newini/pyi2c
Author: Eunchong Kim
Author-email: chariskimec@gmail.com
License: UNKNOWN
Project-URL: Bug Tracker, https://github.com/newini/pyi2c/issues
Platform: UNKNOWN
Classifier: Programming Language :: Python :: 3
Classifier: License :: OSI Approved :: MIT License
Classifier: Operating System :: OS Independent
Requires-Python: >=2.7
License-File: LICENSE
Requires-Dist: smbus2
